validataurus/.gitkeep
validataurus/tests/.gitkeep
validataurus/tests/test_credit_card_validator.py
validataurus/tests/test_date_validator.py
validataurus/tests/test_email_validator.py
validataurus/tests/test_password_validator.py
validataurus/tests/test_phone_validator.py
validataurus/validators/.gitkeep
validataurus/validators/credit_card_validator.py
validataurus/validators/date_validator.py
validataurus/validators/email_validator.py
validataurus/validators/password_validator.py
validataurus/validators/phone_validator.py
validataurus/validators/validator.py
validataurus-0.1.5.dist-info/METADATA
validataurus-0.1.5.dist-info/WHEEL
validataurus-0.1.5.dist-info/RECORD
