Metadata-Version: 2.3
Name: validataurus
Version: 0.1.5
Summary: 
Author: Adam Bonnet
Author-email: adambonnet0@gmail.com
Requires-Python: >=3.9,<4.0
Classifier: Programming Language :: Python :: 3
Classifier: Programming Language :: Python :: 3.9
Classifier: Programming Language :: Python :: 3.10
Classifier: Programming Language :: Python :: 3.11
Classifier: Programming Language :: Python :: 3.12
Classifier: Programming Language :: Python :: 3.13
Requires-Dist: phonenumbers (>=8.13.52,<9.0.0)
